safepyeval/__init__.py
safepyeval/safepyeval.py
safepyeval-0.1.0.dist-info/LICENSE
safepyeval-0.1.0.dist-info/METADATA
safepyeval-0.1.0.dist-info/WHEEL
safepyeval-0.1.0.dist-info/RECORD
